activitystreams/__init__.py
activitystreams/exception.py
activitystreams/utils.py
activitystreams/models/__init__.py
activitystreams/models/activity.py
activitystreams/models/actor.py
activitystreams/models/context.py
activitystreams/models/defobject.py
activitystreams/models/generator.py
activitystreams/models/icon.py
activitystreams/models/image.py
activitystreams/models/medialink.py
activitystreams/models/provider.py
activitystreams/models/tags.py
activitystreams/models/target.py
test/__init__.py
test/test_activity.py
test/test_attachments.py
test/test_defobject.py
test/test_medialink.py
test/test_target.py
test/test_verb.py
activitystreams-0.2.2.dist-info/LICENSE.txt
activitystreams-0.2.2.dist-info/METADATA
activitystreams-0.2.2.dist-info/WHEEL
activitystreams-0.2.2.dist-info/top_level.txt
activitystreams-0.2.2.dist-info/RECORD
